torchclust/__init__.py
torchclust/centroid/__init__.py
torchclust/centroid/kmeans.py
torchclust/centroid/meanshift.py
torchclust/deep/__init__.py
torchclust/deep/som.py
torchclust/density/__init__.py
torchclust/density/dbscan.py
torchclust/density/gmm.py
torchclust/metrics/__init__.py
torchclust/metrics/external.py
torchclust/metrics/internal.py
torchclust/utils/__init__.py
torchclust/utils/datasets.py
torchclust/utils/utils.py
torchclust-1.0.0.dist-info/LICENSE
torchclust-1.0.0.dist-info/METADATA
torchclust-1.0.0.dist-info/WHEEL
torchclust-1.0.0.dist-info/top_level.txt
torchclust-1.0.0.dist-info/RECORD
