Metadata-Version: 2.1
Name: torchclust
Version: 1.0.0
Summary: Scalable Implementations of clustering algorithms written in Pytorch for running on the GPU.
Home-page: https://github.com/danny-1k/torchclust
Author: Daniel Ikechukwu
Author-email: ttdanielik@gmail.com
Keywords: machine learning deep learning pytorch clustering
Classifier: Development Status :: 3 - Alpha
Classifier: Intended Audience :: Developers
Classifier: Intended Audience :: Science/Research
Classifier: Intended Audience :: Education
Classifier: Topic :: Software Development :: Build Tools
Classifier: Topic :: Scientific/Engineering :: Artificial Intelligence
Classifier: License :: OSI Approved :: MIT License
Classifier: Programming Language :: Python :: 3
Requires-Python: >=3.7
License-File: LICENSE
Requires-Dist: torch
